persian_pdf_converter/__init__.py
persian_pdf_converter/imports.py
persian_pdf_converter/pdf_converter.py
src/__init__.py
src/my_pkg/__init__.py
src/my_pkg/resources/__init__.py
src/my_pkg/resources/Tesseract-OCR/ambiguous_words.1.html
src/my_pkg/resources/Tesseract-OCR/ambiguous_words.exe
src/my_pkg/resources/Tesseract-OCR/classifier_tester.1.html
src/my_pkg/resources/Tesseract-OCR/classifier_tester.exe
src/my_pkg/resources/Tesseract-OCR/cntraining.1.html
src/my_pkg/resources/Tesseract-OCR/cntraining.exe
src/my_pkg/resources/Tesseract-OCR/combine_lang_model.1.html
src/my_pkg/resources/Tesseract-OCR/combine_lang_model.exe
src/my_pkg/resources/Tesseract-OCR/combine_tessdata.1.html
src/my_pkg/resources/Tesseract-OCR/combine_tessdata.exe
src/my_pkg/resources/Tesseract-OCR/dawg2wordlist.1.html
src/my_pkg/resources/Tesseract-OCR/dawg2wordlist.exe
src/my_pkg/resources/Tesseract-OCR/libLerc.dll
src/my_pkg/resources/Tesseract-OCR/libarchive-13.dll
src/my_pkg/resources/Tesseract-OCR/libb2-1.dll
src/my_pkg/resources/Tesseract-OCR/libbrotlicommon.dll
src/my_pkg/resources/Tesseract-OCR/libbrotlidec.dll
src/my_pkg/resources/Tesseract-OCR/libbz2-1.dll
src/my_pkg/resources/Tesseract-OCR/libcairo-2.dll
src/my_pkg/resources/Tesseract-OCR/libcrypto-3-x64.dll
src/my_pkg/resources/Tesseract-OCR/libcurl-4.dll
src/my_pkg/resources/Tesseract-OCR/libdatrie-1.dll
src/my_pkg/resources/Tesseract-OCR/libdeflate.dll
src/my_pkg/resources/Tesseract-OCR/libexpat-1.dll
src/my_pkg/resources/Tesseract-OCR/libffi-8.dll
src/my_pkg/resources/Tesseract-OCR/libfontconfig-1.dll
src/my_pkg/resources/Tesseract-OCR/libfreetype-6.dll
src/my_pkg/resources/Tesseract-OCR/libfribidi-0.dll
src/my_pkg/resources/Tesseract-OCR/libgcc_s_seh-1.dll
src/my_pkg/resources/Tesseract-OCR/libgif-7.dll
src/my_pkg/resources/Tesseract-OCR/libgio-2.0-0.dll
src/my_pkg/resources/Tesseract-OCR/libglib-2.0-0.dll
src/my_pkg/resources/Tesseract-OCR/libgmodule-2.0-0.dll
src/my_pkg/resources/Tesseract-OCR/libgobject-2.0-0.dll
persian_pdf_converter-2.3.1.dist-info/METADATA
persian_pdf_converter-2.3.1.dist-info/WHEEL
persian_pdf_converter-2.3.1.dist-info/top_level.txt
persian_pdf_converter-2.3.1.dist-info/RECORD
