Metadata-Version: 2.1
Name: persian_pdf_converter
Version: 2.3.1
Summary: persian_pdf_converter by Mahdi Ramazani is a Python package that converts PDF files to Word documents with OCR support for Persian and English. It automatically downloads and sets up necessary tools like Tesseract and Poppler.
Home-page: https://github.com/mahdiramezanii/persian_pdf_converter
Author: mahdiramezani
Author-email: mahdiramezanii.official@gmail.com
Classifier: Programming Language :: Python :: 3
Classifier: License :: OSI Approved :: MIT License
Classifier: Operating System :: OS Independent
Requires-Python: >=3.6
Requires-Dist: tqdm
Requires-Dist: pdf2image
Requires-Dist: pytesseract
Requires-Dist: Pillow
Requires-Dist: python-docx
Requires-Dist: requests
